{
  "kind": "collectionType",
  "collectionName": "footer_contents",
  "info": {
    "singularName": "footer-content",
    "pluralName": "footer-contents",
    "displayName": "FooterContent",
    "description": ""
  },
  "options": {
    "draftAndPublish": true
  },
  "pluginOptions": {
    "i18n": {
      "localized": true
    }
  },
  "attributes": {
    "footerLinks": {
      "type": "component",
      "repeatable": true,
      "pluginOptions": {
        "i18n": {
          "localized": true
        }
      },
      "component": "footer-section.footer-links"
    },
    "pageLinks": {
      "pluginOptions": {
        "i18n": {
          "localized": true
        }
      },
      "type": "blocks"
    },
    "logo": {
      "type": "media",
      "multiple": false,
      "required": false,
      "allowedTypes": [
        "images",
        "files",
        "videos",
        "audios"
      ],
      "pluginOptions": {
        "i18n": {
          "localized": true
        }
      }
    }
  }
}
